dbcreator/__init__.py
dbcreator/duck_db.py
dbcreator/s3.py
dbcreator-0.0.2.dist-info/LICENSE
dbcreator-0.0.2.dist-info/METADATA
dbcreator-0.0.2.dist-info/WHEEL
dbcreator-0.0.2.dist-info/top_level.txt
dbcreator-0.0.2.dist-info/RECORD
