Metadata-Version: 2.1
Name: dbcreator
Version: 0.0.2
Summary: Package to create a database out of files
Author-email: codenym <isaac.flath@gmail.com>
Project-URL: Homepage, https://github.com/codenym/dbcreator
Project-URL: Issues, https://github.com/codenym/dbcreator/issues
Classifier: Programming Language :: Python :: 3
Classifier: License :: OSI Approved :: MIT License
Classifier: Operating System :: OS Independent
Requires-Python: >=3.8
License-File: LICENSE
Requires-Dist: boto3
Requires-Dist: duckdb
Provides-Extra: dev
Requires-Dist: pytest ; extra == 'dev'
Requires-Dist: twine ; extra == 'dev'
